art/.DS_Store
art/__init__.py
art/classes/__init__.py
art/classes/activitylog.py
art/classes/affiliations.py
art/classes/attrs.py
art/classes/authors.py
art/classes/citation_crawler.py
art/classes/entities.py
art/classes/funders.py
art/classes/networks.py
art/classes/properties.py
art/classes/references.py
art/classes/results.py
art/classes/review.py
art/datasets/.DS_Store
art/datasets/__init__.py
art/datasets/cities/cities_all.txt
art/datasets/cities/cities_en.json
art/datasets/countries/countries_all.txt
art/datasets/countries/country_names.json
art/datasets/languages/.DS_Store
art/datasets/languages/language_codes.txt
art/datasets/languages/language_names.json
art/datasets/languages/languages_en.json
art/datasets/names/all_personal_names.txt
art/datasets/names/first_names.txt
art/datasets/names/last_names.txt
art/datasets/names/nltk_names.txt
art/datasets/stopwords/en_stopwords.txt
art/datasets/stopwords/html_stopwords.txt
art/datasets/stopwords/stopwords.py
art/exporters/.DS_Store
art/exporters/__init__.py
art/exporters/general_exporters.py
art/exporters/network_exporters.py
art/importers/.DS_Store
art/importers/__init__.py
art/importers/bibtex.py
art/importers/crossref.py
art/importers/jstor.py
art/importers/orcid.py
art/importers/pdf.py
art/importers/scopus.py
art/importers/search.py
art/importers/wos.py
art/internet/.DS_Store
art/internet/__init__.py
art/internet/archives.py
art/internet/crawlers.py
art/internet/parsers.py
art/internet/scrapers.py
art/internet/search.py
art/internet/webanalysis.py
art/networks/.DS_Store
art/networks/__init__.py
art/networks/network_functions.py
art/text/.DS_Store
art/text/__init__.py
art/text/information_extraction.py
art/text/textanalysis.py
art/utils/.DS_Store
art/utils/__init__.py
art/utils/basics.py
art/utils/cleaners.py
art/utils/globaltools.py
art/wosstarter_python_client_master/.DS_Store
art/wosstarter_python_client_master/.gitignore
art/wosstarter_python_client_master/.gitlab-ci.yml
academic_review_tool-1.1.0.dist-info/LICENSE
academic_review_tool-1.1.0.dist-info/METADATA
academic_review_tool-1.1.0.dist-info/WHEEL
academic_review_tool-1.1.0.dist-info/entry_points.txt
academic_review_tool-1.1.0.dist-info/top_level.txt
academic_review_tool-1.1.0.dist-info/RECORD
