Metadata-Version: 2.1
Name: academic_review_tool
Version: 1.1.0
Summary: The Academic Review Tool (ART) is a package for performing academic reviews and bibliometric analyses in Python. It offers capabilities for discovering, retrieving, and analysing academic literature at scale.
Author-email: Jamie Hancock <academic_review_tool@outlook.com>
License: GNU GENERAL PUBLIC LICENSE
Project-URL: Homepage, https://github.com/alan-turing-institute/academic_review_tool
Keywords: literature review,academic,bibliometrics,crossref,scopus,web of science
Classifier: Programming Language :: Python
Classifier: Programming Language :: Python :: 3
Requires-Python: >=3.9
License-File: LICENSE
Requires-Dist: beautifulsoup4 >=4.11.1
Requires-Dist: cloudscraper >=1.2.71
Requires-Dist: comcrawl >=1.0.2
Requires-Dist: courlan >=0.9.5
Requires-Dist: crossrefapi >=1.6.0
Requires-Dist: geocoder >=1.38.1
Requires-Dist: geopy >=2.4.1
Requires-Dist: matplotlib >=3.8.2
Requires-Dist: networkx >=2.8.4
Requires-Dist: nltk >=3.8.1
Requires-Dist: numpy >=1.23.0
Requires-Dist: pandas >=1.4.4
Requires-Dist: pyorcid >=1.2.0
Requires-Dist: PyPDF2 >=3.0.1
Requires-Dist: python-docx >=1.1.0
Requires-Dist: python-igraph >=0.10.6
Requires-Dist: python-Levenshtein >=0.25.0
Requires-Dist: pybliometrics >=4.1
Requires-Dist: pybtex
Requires-Dist: igraph >=0.10.6
Requires-Dist: Levenshtein >=0.25.0
Requires-Dist: requests
Requires-Dist: scikit-learn >=1.4.0
Requires-Dist: selectolax >=0.3.17
Requires-Dist: selenium >=4.22.0
Requires-Dist: trafilatura >=1.6.3
Requires-Dist: wayback >=0.4.3
Requires-Dist: selenium >=4.18.1
